ryzenai_onnx_utils/__init__.py
test_ryzenai_onnx_utils-0.0.1.dist-info/METADATA
test_ryzenai_onnx_utils-0.0.1.dist-info/WHEEL
test_ryzenai_onnx_utils-0.0.1.dist-info/top_level.txt
test_ryzenai_onnx_utils-0.0.1.dist-info/RECORD
