Metadata-Version: 2.4
Name: test-ryzenai-onnx-utils
Version: 0.0.1
Summary: onnx utils
Author-email: AMD <support@amd.com>
Requires-Python: >=3.8
